{
  "name": "people_preview",
  "data_type": "people",
  "fields": [
    {
      "name": "firstName"
    },
    {
      "name": "lastName"
    },
    {
      "name": "businessName"
    },
    {
      "name": "city"
    },
    {
      "name": "province"
    },
    {
      "name": "postalCode"
    },
    {
      "name": "country"
    },
    {
      "name": "jobTitle"
    },
    {
      "name": "address"
    },
    {
      "name": "businessCategories",
      "flatten": false
    },
    {
      "name": "licenses",
      "flatten": false,
      "sub_fields": [
        {
          "name": "type"
        },
        {
          "name": "value"
        }
      ]
    },
    {
      "name": "sourceURLs",
      "flatten": false
    },
    {
      "name": "linkedinURL"
    },
    { "name": "keys", "flatten": false }
  ]
}
